odoo/addons/purchase_order_archive/README.rst
odoo/addons/purchase_order_archive/__init__.py
odoo/addons/purchase_order_archive/__manifest__.py
odoo/addons/purchase_order_archive/i18n/pt.po
odoo/addons/purchase_order_archive/i18n/purchase_order_archive.pot
odoo/addons/purchase_order_archive/i18n/zh_CN.po
odoo/addons/purchase_order_archive/models/__init__.py
odoo/addons/purchase_order_archive/models/purchase_order.py
odoo/addons/purchase_order_archive/readme/CONTRIBUTORS.rst
odoo/addons/purchase_order_archive/readme/DESCRIPTION.rst
odoo/addons/purchase_order_archive/readme/USAGE.rst
odoo/addons/purchase_order_archive/static/description/icon.png
odoo/addons/purchase_order_archive/static/description/index.html
odoo/addons/purchase_order_archive/views/purchase_order.xml
odoo12_addon_purchase_order_archive-12.0.1.0.0.99.dev9.dist-info/METADATA
odoo12_addon_purchase_order_archive-12.0.1.0.0.99.dev9.dist-info/WHEEL
odoo12_addon_purchase_order_archive-12.0.1.0.0.99.dev9.dist-info/top_level.txt
odoo12_addon_purchase_order_archive-12.0.1.0.0.99.dev9.dist-info/RECORD
